vistrings/__init__.py
vistrings/__main__.py
vistrings/strings.py
vistrings-0.1.1.dist-info/entry_points.txt
vistrings-0.1.1.dist-info/LICENSE
vistrings-0.1.1.dist-info/WHEEL
vistrings-0.1.1.dist-info/METADATA
vistrings-0.1.1.dist-info/RECORD
